{
  "Comune di Pellezzano": {
    "runs": 82,
    "results": 575,
    "relevant": 1,
    "zero_runs": 0
  },
  "Comune di Salerno": {
    "runs": 82,
    "results": 115,
    "relevant": 0,
    "zero_runs": 0
  },
  "Provincia di Salerno": {
    "runs": 82,
    "results": 135,
    "relevant": 0,
    "zero_runs": 4
  },
  "Comune di Baronissi": {
    "runs": 82,
    "results": 0,
    "relevant": 0,
    "zero_runs": 82
  },
  "Comune di Cava de' Tirreni": {
    "runs": 82,
    "results": 135,
    "relevant": 2,
    "zero_runs": 4
  },
  "Comune di Battipaglia": {
    "runs": 82,
    "results": 0,
    "relevant": 0,
    "zero_runs": 82
  },
  "Comune di Eboli": {
    "runs": 82,
    "results": 0,
    "relevant": 0,
    "zero_runs": 82
  },
  "Comune di Agropoli": {
    "runs": 82,
    "results": 0,
    "relevant": 0,
    "zero_runs": 82
  },
  "Comune di Sapri": {
    "runs": 82,
    "results": 0,
    "relevant": 0,
    "zero_runs": 82
  },
  "Parco Nazionale del Cilento": {
    "runs": 82,
    "results": 0,
    "relevant": 0,
    "zero_runs": 82
  },
  "Regione Campania Agricoltura": {
    "runs": 82,
    "results": 0,
    "relevant": 0,
    "zero_runs": 82
  },
  "Regione Campania Gare": {
    "runs": 82,
    "results": 0,
    "relevant": 0,
    "zero_runs": 82
  },
  "Università di Salerno Collaborazioni": {
    "runs": 82,
    "results": 1543,
    "relevant": 1,
    "zero_runs": 0
  },
  "ASMECOMM Gare": {
    "runs": 82,
    "results": 82,
    "relevant": 0,
    "zero_runs": 0
  },
  "Comune di San Cipriano Picentino Home": {
    "runs": 82,
    "results": 77,
    "relevant": 2,
    "zero_runs": 0
  },
  "Comune di San Cipriano Picentino Avvisi": {
    "runs": 82,
    "results": 410,
    "relevant": 0,
    "zero_runs": 0
  },
  "Comune di San Cipriano Picentino Comunicati": {
    "runs": 82,
    "results": 328,
    "relevant": 0,
    "zero_runs": 0
  },
  "Comune di Fisciano": {
    "runs": 82,
    "results": 0,
    "relevant": 0,
    "zero_runs": 82
  },
  "Comune di Mercato San Severino": {
    "runs": 82,
    "results": 912,
    "relevant": 2,
    "zero_runs": 0
  },
  "Comune di Pontecagnano Faiano": {
    "runs": 82,
    "results": 0,
    "relevant": 0,
    "zero_runs": 82
  },
  "Comune di Bonito": {
    "runs": 82,
    "results": 0,
    "relevant": 0,
    "zero_runs": 82
  },
  "Comune di Cervinara": {
    "runs": 82,
    "results": 0,
    "relevant": 0,
    "zero_runs": 82
  },
  "Comune di Flumeri": {
    "runs": 82,
    "results": 0,
    "relevant": 0,
    "zero_runs": 82
  },
  "Comune di Fontanarosa": {
    "runs": 82,
    "results": 27,
    "relevant": 0,
    "zero_runs": 4
  },
  "Comune di Frigento": {
    "runs": 82,
    "results": 0,
    "relevant": 0,
    "zero_runs": 82
  },
  "Comune di Gesualdo": {
    "runs": 82,
    "results": 0,
    "relevant": 0,
    "zero_runs": 82
  },
  "Comune di Grottaminarda": {
    "runs": 82,
    "results": 27,
    "relevant": 1,
    "zero_runs": 4
  },
  "Comune di Melito Irpino": {
    "runs": 82,
    "results": 0,
    "relevant": 0,
    "zero_runs": 82
  },
  "Comune di Sturno": {
    "runs": 82,
    "results": 0,
    "relevant": 0,
    "zero_runs": 82
  }
}